imate/__version__.py
imate/__init__.py
imate/linear_operator/__init__.py
imate/linear_operator/matrix.py
imate/linear_operator/linear_operator.py
imate/linear_operator/affine_matrix_function.py
imate/functions/smoothstep.h
imate/functions/inverse.h
imate/functions/logarithm.cpp
imate/functions/smoothstep.cpp
imate/functions/py_functions.pyx
imate/functions/gaussian.cpp
imate/functions/logarithm.h
imate/functions/indicator.h
imate/functions/functions.cpp
imate/functions/__init__.pxd
imate/functions/indicator.cpp
imate/functions/inverse.cpp
imate/functions/gaussian.h
imate/functions/py_functions.pypy39-pp73-x86_64-linux-gnu.so
imate/functions/__init__.py
imate/functions/functions.pxd
imate/functions/homographic.h
imate/functions/power.cpp
imate/functions/power.h
imate/functions/exponential.h
imate/functions/functions.h
imate/functions/identity.h
imate/functions/homographic.cpp
imate/functions/identity.cpp
imate/functions/exponential.cpp
imate/functions/py_functions.pxd
imate/_cu_trace_estimator/py_cu_trace_estimator.pypy39-pp73-x86_64-linux-gnu.so
imate/_cu_trace_estimator/py_cu_trace_estimator.pyx
imate/_cu_trace_estimator/cu_lanczos_tridiagonalization.h
imate/_cu_trace_estimator/cu_trace_estimator.pxd
imate/_cu_trace_estimator/cu_orthogonalization.h
imate/_cu_trace_estimator/cu_orthogonalization.pxd
imate/_cu_trace_estimator/__init__.pxd
imate/_cu_trace_estimator/cu_golub_kahn_bidiagonalization.cu
imate/_cu_trace_estimator/cu_trace_estimator.h
imate/_cu_trace_estimator/cu_trace_estimator.cu
imate/_cu_trace_estimator/__init__.py
imate/_cu_trace_estimator/cu_lanczos_tridiagonalization.cu
imate/_cu_trace_estimator/cu_golub_kahn_bidiagonalization.h
imate/_cu_trace_estimator/py_cu_trace_estimator.pxd
imate/_cu_trace_estimator/cu_orthogonalization.cu
imate/device/_cuda.py
imate/device/_info.py
imate/device/__init__.py
imate/device/_device.py
imate/device/_timer.py
imate/device/_memory.py
imate-0.25.2.dist-info/WHEEL
imate-0.25.2.dist-info/LICENSE.txt
imate-0.25.2.dist-info/AUTHORS.txt
imate-0.25.2.dist-info/RECORD
imate-0.25.2.dist-info/top_level.txt
imate-0.25.2.dist-info/METADATA
