Metadata-Version: 2.1
Name: imate
Version: 0.25.2
Summary: Implicit Matrix Trace Estimator. Computes the trace of functions of implicit matrices. Accelerated on CPU and CUDA-capable GPU devices.
Home-page: https://github.com/ameli/imate
Download-URL: https://github.com/ameli/imate/archive/main.zip
Author: Siavash Ameli
Author-email: sameli@berkeley.edu
Project-URL: Documentation, https://github.com/ameli/imate/blob/main/README.rst
Project-URL: Source, https://github.com/ameli/imate
Project-URL: Tracker, https://github.com/ameli/imate/issues
Keywords: matrix-computations matrix-inverse interpolation-techniques
Platform: Linux
Platform: OSX
Platform: Windows
Classifier: Programming Language :: C++
Classifier: Programming Language :: Cython
Classifier: Programming Language :: Python
Classifier: Programming Language :: Python :: 3.9
Classifier: Programming Language :: Python :: 3.10
Classifier: Programming Language :: Python :: 3.11
Classifier: Programming Language :: Python :: 3.12
Classifier: Programming Language :: Python :: Implementation :: CPython
Classifier: Programming Language :: Python :: Implementation :: PyPy
Classifier: Environment :: GPU :: NVIDIA CUDA
Classifier: License :: OSI Approved :: BSD License
Classifier: Operating System :: Unix
Classifier: Operating System :: POSIX
Classifier: Operating System :: POSIX :: Linux
Classifier: Operating System :: Microsoft :: Windows
Classifier: Operating System :: MacOS
Classifier: Natural Language :: English
Classifier: Intended Audience :: Science/Research
Classifier: Intended Audience :: Developers
Classifier: Topic :: Software Development
Classifier: Topic :: Software Development :: Libraries :: Python Modules
Classifier: Topic :: Scientific/Engineering
Classifier: Topic :: Scientific/Engineering :: Mathematics
Classifier: Topic :: Scientific/Engineering :: Artificial Intelligence
Requires-Python: >=3.8
License-File: LICENSE.txt
License-File: AUTHORS.txt
Requires-Dist: numpy >1.11
Requires-Dist: scipy >=1.5
Requires-Dist: matplotlib >=2.0 ; implementation_name == "cpython"
Provides-Extra: docs
Requires-Dist: sphinx ; extra == 'docs'
Requires-Dist: sphinx-math-dollar ; extra == 'docs'
Requires-Dist: sphinx-toggleprompt <0.4 ; extra == 'docs'
Requires-Dist: pydata-sphinx-theme ==0.9.0 ; extra == 'docs'
Requires-Dist: graphviz ; extra == 'docs'
Requires-Dist: sphinx-automodapi ; extra == 'docs'
Requires-Dist: numpydoc ; extra == 'docs'
Requires-Dist: nbsphinx ; extra == 'docs'
Requires-Dist: sphinx-design ; extra == 'docs'
Requires-Dist: sphinx-multitoc-numbering ; extra == 'docs'
Requires-Dist: pandoc ; extra == 'docs'
Requires-Dist: sphinx-prompt ; extra == 'docs'
Requires-Dist: sphinx-copybutton ; extra == 'docs'
Requires-Dist: sphinx-gallery ; extra == 'docs'
Requires-Dist: sphinxext-opengraph ; extra == 'docs'
Requires-Dist: scipy ; extra == 'docs'
Provides-Extra: extra
Requires-Dist: scikit-sparse ; extra == 'extra'
Provides-Extra: test
Requires-Dist: pytest-cov ; extra == 'test'
Requires-Dist: codecov ; extra == 'test'
